anari/pynari.cpython-313-x86_64-linux-gnu.so
anari/__init__.py
anari-1.0.1.dist-info/top_level.txt
anari-1.0.1.dist-info/RECORD
anari-1.0.1.dist-info/METADATA
anari-1.0.1.dist-info/WHEEL
