Metadata-Version: 2.1
Name: anari
Version: 1.0.1
Summary: Python bindings for ANARI
Author: Ingo Wald
Author-email: Ingo Wald <ingowald@gmail.com>
Project-URL: Homepage, https://github.com/ingowald/pynari
Project-URL: Issues, https://github.com/ingowald/pynari/issues
Classifier: Programming Language :: Python :: 3
Classifier: Programming Language :: Python :: 3.6
Classifier: Programming Language :: Python :: 3.7
Classifier: Programming Language :: Python :: 3.8
Classifier: Programming Language :: Python :: 3.9
Classifier: Programming Language :: Python :: 3.12
Classifier: License :: OSI Approved :: MIT License
Classifier: Operating System :: POSIX :: Linux
Requires-Python: >=3.8
